ipagent/__init__.py
ipagent/internal/__init__.py
ipagent/internal/client.py
ipagent/internal/decorators.py
ipagent/internal/geo.py
ipagent/internal/types.py
ipagent-0.1.6.dist-info/licenses/LICENSE
ipagent-0.1.6.dist-info/METADATA
ipagent-0.1.6.dist-info/WHEEL
ipagent-0.1.6.dist-info/top_level.txt
ipagent-0.1.6.dist-info/RECORD
