Metadata-Version: 2.4
Name: ipagent
Version: 0.1.6
Summary: FastAPI dependency: get client IP device browser and geo data
Home-page: https://github.com/allncuz/ipagent
Author: Musharraf Ibragimov
Author-email: meibrohimov@email.com
License: MIT
Classifier: Programming Language :: Python :: 3
Classifier: Framework :: FastAPI
Classifier: Operating System :: OS Independent
Classifier: Intended Audience :: Developers
Classifier: Topic :: Internet :: WWW/HTTP :: HTTP Servers
Requires-Python: >=3.9
License-File: LICENSE
Requires-Dist: fastapi>=0.100
Requires-Dist: httpx>=0.24.0
Requires-Dist: user-agents>=2.2.0
Requires-Dist: pydantic>=2.11.7
Dynamic: author
Dynamic: author-email
Dynamic: classifier
Dynamic: description
Dynamic: description-content-type
Dynamic: home-page
Dynamic: license
Dynamic: license-file
Dynamic: requires-dist
Dynamic: requires-python
Dynamic: summary
